odoo8_addon_event_registration_cancel_reason-8.0.1.0.0.99.dev10-py2.7-nspkg.pth
odoo_addons/event_registration_cancel_reason/__openerp__.py
odoo_addons/event_registration_cancel_reason/__init__.py
odoo_addons/event_registration_cancel_reason/README.rst
odoo_addons/event_registration_cancel_reason/security/ir.model.access.csv
odoo_addons/event_registration_cancel_reason/models/event_registration.py
odoo_addons/event_registration_cancel_reason/models/__init__.py
odoo_addons/event_registration_cancel_reason/i18n/es.po
odoo_addons/event_registration_cancel_reason/wizard/event_registration_cancel_log_reason_view.xml
odoo_addons/event_registration_cancel_reason/wizard/__init__.py
odoo_addons/event_registration_cancel_reason/wizard/event_registration_cancel_log_reason.py
odoo_addons/event_registration_cancel_reason/views/event_registration_view.xml
odoo_addons/event_registration_cancel_reason/tests/test_event_registration_cancel_reason.py
odoo_addons/event_registration_cancel_reason/tests/__init__.py
odoo_addons/event_registration_cancel_reason/static/description/icon.png
odoo8_addon_event_registration_cancel_reason-8.0.1.0.0.99.dev10.dist-info/top_level.txt
odoo8_addon_event_registration_cancel_reason-8.0.1.0.0.99.dev10.dist-info/WHEEL
odoo8_addon_event_registration_cancel_reason-8.0.1.0.0.99.dev10.dist-info/RECORD
odoo8_addon_event_registration_cancel_reason-8.0.1.0.0.99.dev10.dist-info/metadata.json
odoo8_addon_event_registration_cancel_reason-8.0.1.0.0.99.dev10.dist-info/DESCRIPTION.rst
odoo8_addon_event_registration_cancel_reason-8.0.1.0.0.99.dev10.dist-info/METADATA
odoo8_addon_event_registration_cancel_reason-8.0.1.0.0.99.dev10.dist-info/namespace_packages.txt
